<?xml version="1.0" encoding="UTF-8" standalone="yes"?>
<scenarioConfiguration  domain="APIMAnalytics"
	name="AbnormalTierAvailabilityAlert" scenario="AbnormalTierUsageAlert">
	<description>Abnormal tier usage alerts</description>
	<parameters>
		<parameter name="percentile">
			<value>0.05</value>
		</parameter>
		<parameter name="alertStartDate">
			<value>12/2/2016</value>
		</parameter>
		<parameter name="daysConsiderForAbnormalTierAvailability">
			<value>5</value>
		</parameter>
		<parameter name="daysConsiderForPercentilesCalculation">
			<value>30</value>
		</parameter>
        <parameter name="severity">
            <value>2</value>
        </parameter>
	</parameters>
</scenarioConfiguration>
